intervals_mcp_server/server.py
mseep_intervals_mcp_server-0.1.4.dist-info/METADATA
mseep_intervals_mcp_server-0.1.4.dist-info/WHEEL
mseep_intervals_mcp_server-0.1.4.dist-info/licenses/LICENSE
mseep_intervals_mcp_server-0.1.4.dist-info/RECORD
