Metadata-Version: 2.4
Name: mseep-intervals-mcp-server
Version: 0.1.4
Summary: A Model Context Protocol server for Intervals.icu
Project-URL: Homepage, https://github.com/mvilanova/intervals-mcp-server
Project-URL: Bug Tracker, https://github.com/mvilanova/intervals-mcp-server/issues
Author-email: mseep <support@skydeck.ai>
License: GPL-3.0-only
License-File: LICENSE
Keywords: ai,cycling,intervals,mcp,running
Classifier: Development Status :: 3 - Alpha
Classifier: Intended Audience :: Developers
Classifier: Programming Language :: Python :: 3
Classifier: Programming Language :: Python :: 3.12
Classifier: Topic :: Software Development :: Libraries
Requires-Python: >=3.12
Requires-Dist: httpx>=0.25.0
Requires-Dist: mcp[cli]>=1.4.0
Requires-Dist: python-dotenv>=1.0.0
Provides-Extra: dev
Requires-Dist: hatch; extra == 'dev'
Requires-Dist: mypy>=1.0.0; extra == 'dev'
Requires-Dist: pre-commit; extra == 'dev'
Requires-Dist: pytest-asyncio>=0.21; extra == 'dev'
Requires-Dist: pytest-mock==3.12.0; extra == 'dev'
Requires-Dist: pytest>=8.3.5; extra == 'dev'
Requires-Dist: ruff>=0.1.0; extra == 'dev'
